[{"spec":{"publisher":{"id":"newsis","name":"뉴시스","type":"통신사","url":"https://newsis.com"},"title":"연예","categories":["entertainment"],"url":"https://newsis.com/RSS/entertain.xml"},"title":"&#039;한산:용의 출현&#039; 하루 66만명…누적 200만명 넘는다","partialText":"<p><a href=\"http://image.newsis.com/2022/07/26/NISI20220726_0001050307_web.jpg?rnd=20220726160633\"><img border=\"0\" src=\"http://image.newsis.com/2022/07/26/NISI20220726_0001050307_web.jpg?rnd=20220726160633\" width=\"130\" /></a></p><br />[서울=뉴시스] 손정빈 기자 = 영화 &#039;한산:용의 출현&#039;이 하루에만 60만명이 넘는 관객을 끌어모으며 160만 관객을 돌파했다. 개봉 첫 주말에 누적 200만명을 넘길 것으로 예상된다.<br /><br />영화진흥위원회에 따르면, &#039;한산:용의 출현&#039;은 30일 66만1073명을 추가하며 누적 관객수 161만4626명을 기록 중이다. 영화는 31일 오전 9시 현재 예매 관객수 24만명을 확보해놓은 상태다. 주말 중 200만 관객 돌파는 무난할 것으로 예상된다.<br /><br />&#039;한산:용의 출현&#039;은 올해 국내 개봉 영화 행흥 순위 8위로 뛰어올랐다. 1위는 &#039;범죄도시2&#039;(1269만명) 2위 &#039;탑건:매버릭&#039;(693만명), 3위 &#039;닥터 스트레인지:대혼돈의 멀티버스&#039;(588만명), 4위 &#039;쥬라기 월드:도미니언&#039;(283만명), 5위 &#039;마녀2&#039;(280만명), 6위 &#039;토르:러브 앤 썬더&#039;(270만명), 8위 &#039;헤어질 결심&#039;(164만명) 순이다.<br /><br />&#039;한산:용의 출현&#039;은 2014년 1761만 관객이 봐 역대 박스오피스 1위에 올라 있는 &#039;명량&#039;의 후속작이다. 전작과 마찬가지로 김한민 감독이 연출을 맡았다. 1592년 임진왜란이 발발한 후 이순신 장군과 조선 수군이 한산도 앞바다에서 왜 수군을 격퇴한 한산도 해전을 그린다. 이순신 역은 배우 박해일이, 왜군 장수 와키자카는 변요한이 연기했다. 이밖에 김성규·안성기·손현주·김성균·김향기·옥택연 등이 출연했다. 제작비만 300억원 이상 투입된 대작이다.<br /><br />이밖에 박스오피스 순위는 2위 &#039;미니언즈2&#039;(12만5943명·누적 138만명), 3위 &#039;탑건:매버릭&#039;(11만9045명·누적 693만명), 4위 &#039;외계+인 1부&#039;(7만3678명·누적 128만명), 5위 &#039;뽀로로 극장판 드래곤캐슬 대모험&#039;(4만6922명·누적 12만명) 순이었다.<br />\n◎공감언론 뉴시스 jb@newsis.com","date":"2022-07-31T08:49:35.000Z","url":"http://www.newsis.com/view?id=NISX20220731_0001962332"},{"spec":{"publisher":{"id":"newsis","name":"뉴시스","type":"통신사","url":"https://newsis.com"},"title":"연예","categories":["entertainment"],"url":"https://newsis.com/RSS/entertain.xml"},"title":"뉴진스, &#039;민희진 표&#039; 정반합 상징…K팝 걸그룹 변증법 새 공식","partialText":"<p><a href=\"http://image.newsis.com/2022/07/22/NISI20220722_0001047521_web.jpg?rnd=20220722081828\"><img border=\"0\" src=\"http://image.newsis.com/2022/07/22/NISI20220722_0001047521_web.jpg?rnd=20220722081828\" width=\"130\" /></a></p>[서울=뉴시스]이재훈 기자 = 민희진 어도어(ADOR, All Doors One Room의 약자) 대표이사가 첫 제작한 신인 걸그룹 &#039;뉴진스(NewJeans)&#039;가 K-팝 공식을 깼다는 건 반은 맞고 반은 틀리다. <br /><br />민 대표가 지난해 말 tvN &#039;유 퀴즈 온 더 블럭&#039; 출연했을 당시 전개한 &#039;정반합(正反合)&#039; 삼단계 논리를 뉴진스에 적용하면 그런 결론이 도출된다. <br /><br />민 대표는 그룹 &#039;방탄소년단&#039;(BTS)을 탄생시킨 하이브(HYBE)로 옮기기 전(어도어는 하이브가 론칭한 레이블) SM엔터테인먼트에서 크리에이티브 디렉터 겸 등기이사 자리까지 올랐다. 2002년 SM 공채 평사원으로 입사해서 이 같은 결과를 이뤄낸 입지전적인 인물이다. 가수로 따지면, 올해가 데뷔 20주년인 셈. <br /><br />민 대표의 작업을 대표하는 비주얼 디렉팅은 SM의 2·3세대를 대표하는 걸그룹들인 &#039;소녀시대&#039;·&#039;f(x)&#039;·&#039;레드벨벳&#039;을 통해 이뤄냈다.   <br /><br />소녀시대·f(x)·레드벨벳의 관계가 바로 정반합을 이룬다. 정반합은 헤겔의 변증법(辨證法)을 도식화한 논리다. 변증법은 모순 또는 대립을 근본원리로, 사물의 운동을 설명하는 논리. <br /><br />그럼 우선 정반합을 풀어보자. 역사는 기존 질서의 모순을 지적하고 반대하면서 발전해나간다. 헤겔 식으로 말하자면 이것이 정반합이다. 기존 기본적인 구도가 정(正)이라고 할 때 시간이 흐른 뒤 이것과 상반되는 반(反)이 만들어진다. 이 정(正)과 반(反)이 갈등을 겪으면서 합(合)으로 초월한다는 논지다.<br /><br /><p><a href=\"http://image.newsis.com/2022/07/31/NISI20220731_0001053460_web.jpg?rnd=20220731074526\"><img border=\"0\" src=\"http://image.newsis.com/2022/07/31/NISI20220731_0001053460_web.jpg?rnd=20220731074526\" width=\"130\" /></a></p>민 대표에 따르면, 소녀시대는 이전까지 정형화된 느낌이 있었던 걸그룹의 반(反)이었다. 소녀시대 전의 걸그룹들은 비현실적인 느낌이 있었다는 것이다. 그런데 소녀시대는 &#039;지(Gee)&#039; 활동에서 화장기를 뺀 채 흰 티셔츠·스키니 진 등 일상에서 볼 수 있는 의상을 입고 친근함을 내세웠다. &#039;지&#039;는 소녀시대가 국민 걸그룹 반열에 오르는 발판이 됐다. <br /><br />그렇게 소녀시대가 &#039;걸그룹의 정석&#039;이라 불리며 정(正)이 된 상황. 역작 &#039;일렉트릭 쇼크&#039;(미니 2집) &#039;핑크테이프&#039;(정규 2집)로 기억되는 f(x)는 그런 소녀시대의 반(反)이었다. 개성 강한 멤버들이 뭉쳤던 f(x)는 전형적인 아이돌의 모습을 탈피했다. <br /><br />이후 데뷔한 레드벨벳은 소녀시대와 f(x)의 합(合)이었다. 팀명부터 &#039;강렬한 컬러 레드와 여성스럽고 부드러운 느낌의 벨벳&#039;의 조합이다. f(x)와 소녀시대의 장점을 섞은 셈이었다. f(x)보다 친근했고, 소녀시대보다 비현실적이었다. <br /><br />그렇다면 지난 22일 데뷔 EP &#039;뉴 진스(New Jeans)&#039;의 타이틀곡 &#039;어텐션(Attention)&#039; 뮤직비디오를 공개하면서 데뷔한 뒤 일주일 만에 대세 걸그룹이 된 뉴진스는 어떤 정반합 과정을 겪었나. <br /><br />일단 K팝 걸그룹 4세대 후반군에 묶일 뉴진스는 3세대, 4세대와 정반합이 됐다. <br /><br /><p><a href=\"http://image.newsis.com/2022/07/31/NISI20220731_0001053451_web.jpg?rnd=20220731054358\"><img border=\"0\" src=\"http://image.newsis.com/2022/07/31/NISI20220731_0001053451_web.jpg?rnd=20220731054358\" width=\"130\" /></a></p>한 때 &#039;트레블&#039;로 묶이기도 했던 트와이스, 레드벨벳, 블랙핑크 같은 3세대 K팝 걸그룹은 누군가의 롤모델로 자리매김했다. 틴에이저들이 따라하고 싶은 우상으로서 역할을 했고 여전히 하고 있으면서 정(正)이 됐다. 반면 에스파(aespa), 있지(ITZY), 아이브(IVE) 같은 4세대 걸그룹들은 3세대의 반(反)이다. 세계관을 설정하고 그 안에서 팬덤이 &#039;유희&#039;를 즐기는 형태로 인기를 누리고 있다.  <br /><br />뉴진스는 이 3·4세대의 장점들을 흡수한다. 누가 봐도 아이돌일 수밖에 없는 민지(18)·하니(18)·다니엘(17)·해린(16)·혜인(14)의 아름다운 얼굴과 사랑스러움은 3세대의 아이돌의 그것처럼 선망의 대상이다. 또 &#039;어텐션&#039; &#039;하이프 보이&#039; &#039;허트(Hurt)&#039; 등 미리 공개된 뮤직비디오와 가사에서 알 수 있듯 이들은 틴에이저의 일상으로 들어와 공감대를 형성하고 &#039;현실적인 세계관&#039;을 만든다. <br /><br />일부에선 틴에이저에 대한 민 대표의 대상화 또는 전시를 지적하기도 한다. 그런데 엄밀히 말하면, 가닿기 힘든 지적이다. 기성 세대가 기획을 한 이미지이나, 뉴진스 콘텐츠 안에서 다섯 멤버들이 바라보고 바라봄을 당하는 대상은 또래이기 때문이다. 성인의 시선으로 재단화된 게 아니라는 얘기다. <br /><br />하이브와 어도어는 뉴진스가 K-팝 공식을 깼다고 얘기하고 있는데, 이것 역시 따지면 정확하지 않다. 티징 이미지가 아닌 뮤직비디오가 제일 먼저 공개한 콘텐츠였다는 것이 최근 K팝 프로모션 공식을 깬 점이기는 하다. 그런데 사실 뉴진스는 K팝의 걸그룹 성공 공식을 모두 흡수한 팀이다. <br /><br />&quot;사람들이 좋아하는 걸그룹 요소들을 기가막히게 잘 버무려놓았다&quot;(1세대 걸그룹부터 모두 좋아해온 30대 회사원)는 평이 괜히 나오는 것이 아니다. <br /><br /><p><a href=\"http://image.newsis.com/2022/07/31/NISI20220731_0001053452_web.jpg?rnd=20220731054420\"><img border=\"0\" src=\"http://image.newsis.com/2022/07/31/NISI20220731_0001053452_web.jpg?rnd=20220731054420\" width=\"130\" /></a></p>1990년대 혹은 더 거슬러 올라가 1980년대 아이돌을 선망하는 이들이 방에 걸어놓았을 법한, 청량하고 청순한 이미지들. 세련된 동시에 담백한 팝 댄스(&#039;어텐션&#039;)·뭄바톤(Moombahton)과 일렉트로팝(ElectroPop)의 근사한 조합(&#039;하이프 보이&#039;)·통통 튀는 신스 댄스 팝(&#039;쿠키&#039;)·아련하면서도 사랑스러운 R&B(&#039;허트&#039;) 등의 명료한 음악. 몽글몽글한 &#039;Y2K&#039;(1900년대 후반부터 2000년대 초까지 유행한 밀레니얼) 감성과 Z세대 감성의 아련하고 낭만적인 만남. <br /><br />지금까지 K팝 걸그룹 아이돌이 각각 잘해온 것들을 민희진 식 감성으로 애틋하게 해석해 더 맵시 있게 만들어낸 결과물이다. <br /><br />특히 &#039;하이틴의 뉴트로&#039;라고 명명할 수 있는 비주얼 디렉팅이 영리한 한수다. 예전 향수를 Z세대 앞에 아무렇지 않게 배치하면서 세대 간 음악적 연대(連帶)를 심어놓는 선순환이 돋보인다.  <br /><br />뉴진스와 팬들의 스마트폰 전용 소통 애플리케이션 &#039;포닝(Phoning)&#039;이 예다. 어도어와 하이브의 팬 커뮤니티 플랫폼 위버스가 합작해 만든 포닝은 뉴진스와 팬들이 하나의 폰을 공유한다는 콘셉트로 개발됐다. 그런데 유저 인터페이스(UI)가 구식 휴대폰을 떠올리게 한다. 첫 화면의 이모티콘 배치 등도 최근 스마트폰 앱의 세련됨이 아닌 복고풍이다.  <br /><br />특히 앞서 진행한 EP &#039;뉴진스&#039; 세 가지 버전 예약판매에서 소셜 미디어 등에서 특히 화제가 된 건 멤버들의 사진으로 꾸민 핀업북(PIN-UP BOOK), 포토카드, CD를 원형 가방에 담은 구성인 &#039;뉴 진스 백(New Jeans Bag)&#039; 버전이었다. 최근 세대는 경험하지 못한 CD플레이어(Compact Disk Player·CDP) 가방에 대한 향수를 자극했다. <br /><br /><p><a href=\"http://image.newsis.com/2022/07/25/NISI20220725_0001049550_web.jpg?rnd=20220725185239\"><img border=\"0\" src=\"http://image.newsis.com/2022/07/25/NISI20220725_0001049550_web.jpg?rnd=20220725185239\" width=\"130\" /></a></p>이와 관련 민 대표는 인스타그램에 &quot;제가 어린 시절에 CDP를 항상 들고 다녔는데, 마땅히 맘에 드는 사이즈의 가방이 없어 예쁜 파우치를 많이 찾았다&quot;면서 &quot;그때 기억으로 음반을 가방으로 만들고 싶다는 생각을 하게 됐고, 그래서 CDP가 들어갈 수 있는 사이즈로 제작했다&quot;고 설명했다. <br /><br />&quot;CD 20여장이 들어갈 수 있는 묵직한 CD 케이스를 들고 다녔다&quot;처럼, 소셜 미디어에는 1970~1980년대 언저리에 태어난 이들의 CDP와 CD가방에 대한 추억담이 공유되기도 했다. <br /><br />음악 소식·뉴스·리뷰 등을 전하는 플랫폼 &#039;제너레이트&#039;를 운영하는 김도헌 대중음악평론가(한국대중음악상(KMA) 선정위원)는 &quot;뉴진스가 Y2K, 90년대 문화를 차용했는데 유행한다고 해서 따른 게 아닌 그 시대를 산 사람의 향수가 자연스럽고 매끈하게 같이 봉합돼 있다&quot;면서 &quot;CDP 가방이나 옛날 휴대폰 모양의 소통 앱 등 디테일이 하나하나 심상치 않다&quot;고 봤다. <br /><br />김 평론가는 이와 함께 수수께끼 같은 티저만 공개했다가 바로 타이틀곡 뮤직비디오를 공개한 어도어와 뉴진스의 데뷔 방식에 대해 &quot;노래와 콘텐츠에 대한 민희진 대표의 자신감&quot;이라고 해석했다. <br /><br />실제 음악과 콘셉트의 완성도가 높았던 이유는 민 대표와 꾸준히 호흡을 맞춰온 &#039;민희진 사단&#039;이 이번에도 힘을 실었기 때문이다. &#039;어텐션&#039; &#039;하이프 보이&#039; &#039;허트&#039;에 프로듀서 겸 DJ 이오공(250·이호형·40)이 참여해 눈길을 끌었는데 그는 민 대표가 음악과 관련 절대적으로 신뢰를 보내는 인물로 알려졌다. 특히 250은 최근 트로트를 힙합게 해석해 해외에서도 호평 받은 첫 정규 음반 &#039;뽕&#039;의 주인공이다. 또 f(x), 보아, NCT 127 등 SM 소속 그룹들과 있지 등 JYP 그룹 등 인기 K팝 팀들과 꾸준히 작업을 해왔다.<br /><br /><p><a href=\"http://image.newsis.com/2022/07/26/NISI20220726_0001049631_web.jpg?rnd=20220726083937\"><img border=\"0\" src=\"http://image.newsis.com/2022/07/26/NISI20220726_0001049631_web.jpg?rnd=20220726083937\" width=\"130\" /></a></p>이와 함께 신동훈 바이스 프레지던트(VP), 김예민 수석 크리에이티브 디렉터, 김나연 크리에이티브 디렉터 등 SM 시절부터 합을 맞춰온 비주얼 스태프들도 어도어에서 함께 일하고 있다. <br /><br />이로 인해 방시혁 의장이 이끄는 하이브 레이블즈 내 두 레이블에서 비슷한 시기에 론칭한 걸그룹의 &#039;선의의 경쟁&#039;도 4세대 걸그룹 구도에서 빼놓을 수 없는 관전 포인트가 됐다. <br /><br />하이브 레이블즈인 쏘스뮤직은 지난 5월 방 의장과 소성진 쏘스뮤직 대표가 제작을 주도한 &#039;르세라핌(LE SSERAFIM)&#039;을 선보였다. 한일 프로젝트 걸그룹 &#039;아이즈원&#039; 출신 김채원·사쿠라가 주축이 된 르세라핌의 데뷔 앨범 &#039;피어리스(FEARLESS)&#039;는 K팝 그룹의 인기 지표 중 하나인 초동(발매 일주일 판매량) 30만장으로 데뷔 걸그룹 기록을 썼다. <br /><br />그런데 뉴진스의 데뷔 앨범 &#039;뉴 진스(New Jeans)&#039;는 예약판매 사흘째인 지난 27일 기준 선주문량 44만4000장을 기록했다. 선주문 수량이 일주일에 다 소진되는 걸 감안하면 데뷔 걸그룹 초동 신기록이 확실시된다. 이밖에도 각종 지표에서 데뷔 걸그룹 신기록을 예고하고 나섰다. <br /><br />같은 레이블에서 비슷한 시기에 신인 걸그룹을 론칭하는 건 드문 일이다. 하지만 방 의장·소 대표의 색깔과 민 대표의 색깔이 차이가 커 팬덤이 겹치기보다, 서로 &#039;선의의 경쟁&#039;을 하며 시너지를 낼 것이라는 예상이다.<br /><br /><p><a href=\"http://image.newsis.com/2022/07/22/NISI20220722_0001047522_web.jpg?rnd=20220722081850\"><img border=\"0\" src=\"http://image.newsis.com/2022/07/22/NISI20220722_0001047522_web.jpg?rnd=20220722081850\" width=\"130\" /></a></p>김도헌 평론가는 &quot;르세라핌은 모던한 캐치프레이즈를 내세우고 있고, 뉴진스는 하이브 소속이기는 하지만 민희진 대표의 어도어 색깔을 극대화한 팀&quot;이라면서 &quot;걸그룹의 다양성을 살리고 다양한 카드를 만들어놓았다는 점에서 하이브의 영리한 전략&quot;이라고 봤다. <br /><br />뉴진스가 하이브에게든 K팝계에게든 데뷔하자마자 걸그룹 다양성에 일조하고 있는 건 사실이다. 민 대표는 뉴진스라는 팀 이름에 대해 &quot;매일 찾게 되고 언제 입어도 질리지 않는 진(Jean)처럼 시대의 아이콘이 되겠다는 포부를 담았다&quot;고 했다. 이 이름에는 또 다른 의미가 담겨 있다. 뉴 진스(New Genes). 즉 &#039;새로운 유전자&#039;다. <br /><br />뉴진스의 &#039;뉴 진스&#039;는 내달 8일 오프라인에 발매된다. 음원은 앨범 발매에 앞서 같은 달 1일 오후 6시 공개한다.<br />\n◎공감언론 뉴시스 realpaper7@newsis.com","date":"2022-07-31T08:06:36.000Z","url":"http://www.newsis.com/view?id=NISX20220728_0001960394"},{"spec":{"publisher":{"id":"newsis","name":"뉴시스","type":"통신사","url":"https://newsis.com"},"title":"연예","categories":["entertainment"],"url":"https://newsis.com/RSS/entertain.xml"},"title":"산다라박 &quot;비혼이지만 연애상담은 필요&quot;…왜?","partialText":"<p><a href=\"http://image.newsis.com/2022/07/30/NISI20220730_0001053394_web.jpg?rnd=20220730181217\"><img border=\"0\" src=\"http://image.newsis.com/2022/07/30/NISI20220730_0001053394_web.jpg?rnd=20220730181217\" width=\"130\" /></a></p><br />[서울=뉴시스]송윤세 기자 = 가수 산다라 박이 비혼주의라고 선언했다. <br /><br />31일 오후 5시 방송하는 MBC &#039;복면가왕&#039;에서 한 복면가수가 &quot;연애 상담을 1000건 정도 해줬다&quot;며 연애 상담에 자신감을 밝히자 판정단석의 반응이 뜨거워졌다. 특히 산다라 박은 &quot;제가 비혼이지만 연애 상담은 정말 필요하다&quot;고 깜짝 발언을 해 모두를 놀라게 했다. 그럼에도 &quot;소개팅은 시켜주신다면 열심히 하겠다!&quot;며 소개팅에 대한 의외의 열의를 보여 스튜디오를 웃음바다로 만들었다. <br /><br />아울러 적우를 감동시킨 복면가수도 등장했다. 적우는 한 복면가수의 무대가 진행되는 내내 깊게 몰입한 모습을 보였다. 적우는 &quot;이 노래는 &#039;영&#039;이 맑아야만 부를 수 있는 곡&quot;이라며 복면가수의 영혼을 칭찬한 것은 물론 &quot;누가 이 노래를 부를 수 있을지 궁금했는데 듣는 내내 소름이 끼쳤다. 마치 콘서트장에 와 있는 것 같았다&quot;며 끝없는 찬사를 보냈다. 유영석 역시 &quot;영혼이 맑기도 하지만, 한이 느껴지기도 한다. 무대가 굉장히 세다&quot;며 칭찬을 보탰다. <br /><br />또 판정단을 고뇌에 빠트린 &#039;막상막하&#039; 가창력 대결도 펼쳐졌다. 두 복면가수가 각자의 장점을 살려 준비한 무대가 모두 끝나자, 선택을 앞둔 판정단은 깊은 고민에 빠졌다. 재즈가수 웅산은 &quot;원곡자가 생각나지 않는 무대, 절대 사라지지 않는 빛 같은 무대였다&quot;며 두 복면가수를 향한 칭찬을 아끼지 않았다. 끝까지 선택을 망설인 산다라 박은 &quot;두 분 다 너무 훌륭한 무대를 보여주셔서 승패가 의미가 없는 것 같다&quot;며 두 사람 모두에게 박수를 보냈다.<br />\n◎공감언론 뉴시스 knaty@newsis.com","date":"2022-07-31T06:30:00.000Z","url":"http://www.newsis.com/view?id=NISX20220730_0001962178"},{"spec":{"publisher":{"id":"newsis","name":"뉴시스","type":"통신사","url":"https://newsis.com"},"title":"연예","categories":["entertainment"],"url":"https://newsis.com/RSS/entertain.xml"},"title":"디지털 화폐 전문가 &quot;비교적 안전한 조각투자 있어&quot;…뭐?","partialText":"<p><a href=\"http://image.newsis.com/2022/07/30/NISI20220730_0001053390_web.jpg?rnd=20220730174817\"><img border=\"0\" src=\"http://image.newsis.com/2022/07/30/NISI20220730_0001053390_web.jpg?rnd=20220730174817\" width=\"130\" /></a></p><br />[서울=뉴시스]송윤세 기자 = 디지털 화폐 전문가 홍기훈 교수가 &#039;디지털 자산&#039;에 대한 모든 것을 파헤친다.<br /><br />31일 오전 10시30분 방송되는 JTBC &#039;차이나는 클라스-질문 있습니다&#039;에서는 홍 교수가 출연해 디지털 자산에 관련해 강의한다. 우크라이나·러시아 전쟁은 멈출 줄 모르고, 세계 경제 상황은 점점 나빠지며 코인시장과 주식시장이 불안정해지고 있다. 설상가상으로 트위터 창업자 잭 도시의 첫 트윗 NFT가 35억 원에 팔렸지만 현재는 837만원으로 가치가 떨어지기도 했다. 이에 홍 교수는 디지털 자산의 미래에 대한 답은 물론, 루나-테라 사태의 진실과 돈을 잃지 않고 투자하는 방법까지 알려준다.<br /><br />&#039;디지털 자산&#039;이란 부동산 같은 실물 자산이 아닌, 디지털 형태의 가치를 가진 것을 말한다. NFT 아트, 코인, 가상 부동산 등이 디지털 자산의 예다. 세계가 변하면서 투자 트렌드가 바뀌고, 다양한 디지털 자산 상품들도 등장했다. 그중 대표적인 것은 &#039;조각투자&#039;다. 조각투자의 장점은 고가의 상품들을 소액으로 투자할 수 있는 것. 조각투자의 한 종류인 음악저작권을 거래하는 모 업체의 경우 거래액이 2018년 10억에서 2021년 91억으로 상승하며 큰 인기를 끌고 있다. 그 외에도 소, 슈퍼카, 부동산 등 다양한 디지털 투자 상품들이 존재한다.<br /><br />하지만 조각투자에도 단점은 존재한다. 홍 교수는 &quot;블록체인 기술이 있는 것처럼 홍보만 하는 경우가 많다&quot;며 조각투자의 위험성을 강조했다. 또 &quot;조각투자의 위험성은 항상 존재하며 블록체인 기술에 대한 신뢰가 문제&quot;라고 덧붙였다. 그렇다면 안전한 조각투자는 없는냐는 출연자들의 물음에 홍 교수는 &quot;비교적 안전한 조각투자가 있다&quot;고 밝혔다.<br />\n◎공감언론 뉴시스 knaty@newsis.com","date":"2022-07-31T06:04:00.000Z","url":"http://www.newsis.com/view?id=NISX20220730_0001962187"},{"spec":{"publisher":{"id":"newsis","name":"뉴시스","type":"통신사","url":"https://newsis.com"},"title":"연예","categories":["entertainment"],"url":"https://newsis.com/RSS/entertain.xml"},"title":"[인터뷰]이병헌 &quot;개봉이 얼마나 감사한 일인지 다시 느껴요&quot;","partialText":"<p><a href=\"http://image.newsis.com/2022/07/29/NISI20220729_0001053039_web.jpg?rnd=20220729155421\"><img border=\"0\" src=\"http://image.newsis.com/2022/07/29/NISI20220729_0001053039_web.jpg?rnd=20220729155421\" width=\"130\" /></a></p><br />[서울=뉴시스] 손정빈 기자 = 배우 이병헌(52)의 필모그래피는 &#039;남산의 부장들&#039;에서 멈춰섰다. &#039;남산의 부장들&#039;은 코로나 사태 직전인 2020년 1월에 개봉했다. 이 작품을 끝으로 이병헌이 나오는 영화를 볼 수 없었다. 물론 그는 드라마에 나왔고, 아직 개봉하지 않은 다양한 영화에 참여해 계속 연기했다. 하지만 그의 영화는 약 30개월 간 관객을 만나지 못했다. 이병헌이 나오는 영화는 1995년 &#039;누가 나를 미치게 하는가!&#039; 이후 25년 간, 2003년 딱 한 해만 빼고 매년 있었다.<br /><br />새 영화 &#039;비상선언&#039; 개봉을 앞두고 이병헌을 만났다. 그는 &quot;시사회를 마치고 무대에 올라 관객 여러분께 인사를 드리고나니 마음 안에서 뭔가 들끓는 느낌을 받았다&quot;고 말했다. 그러면서 &quot;이 영화가 극장에 걸리기를 손꼽아 기다렸다&quot;고 덧붙였다. &quot;팬데믹이 있기 전까지 이게 저의 일상이고 루틴이었죠. 이런 상황을 오랜만에 마주하니까 새삼 새롭더라고요. 내가 지나왔던 순간들이 참 행복한 일들이었다는 걸 새삼 알게 됐어요. 감사함을 많이 느껴요.&quot;<br /><br />이병헌이 한국영화계에 자리를 비운 그 시기에 온라인 스트리밍 시대가 열렸다. 관객이 영화관을 찾지 않게 되자 극장은 물론이고 영화계 전체가 말 그대로 초토화됐다. 그 역시 이대로 영화의 시대는 막을 내리는 건 아닌지 걱정했다고 했다. &quot;극장이 계속 남아 있기는 하는 건지, OTT가 주류가 되는 시대가 온 건지, 별의별 생각을 다했어요. 아마 저를 포함한 배우들 그리고 이 산업에 종사하는 모든 분이 비슷한 생각을 했을 겁니다. 그런데 최근에 잘되는 영화들이 또 나오더라고요. 그런 모습을 보면서 극장은 죽지 않았구나, 영화는 계속되는구나, 라는 희망을 갖게 됐습니다. 그렇게 됐으면 좋겠고, 그렇게 될 거예요.&quot;<br /><p><a href=\"http://image.newsis.com/2022/07/29/NISI20220729_0001053042_web.jpg?rnd=20220729155520\"><img border=\"0\" src=\"http://image.newsis.com/2022/07/29/NISI20220729_0001053042_web.jpg?rnd=20220729155520\" width=\"130\" /></a></p><br />그런 희망을 갖고 이병헌이 이번에 선보이는 영화 &#039;비상선언&#039;은 국내에서 한 번도 시도된 적 없는 항공재난영화다. 제작비 약 300억원이 투입된 대작이다보니 대형 스크린이 있는 영화관에서 봐야 더 큰 재미를 느낄 수 있는 말 그대로 영화라는 말이 어울리는 작품이다. 이병헌은 딸과 함께 비행기에 올랐다가 비행기 테러 피해를 입는 &#039;재혁&#039;을 연기했다. 재혁은 기내가 대혼란에 휩싸이는 상황에서도 딸을 지키기 위해 고군분투한다.<br /><br />&quot;저도 아들을 둔 아빠잖아요. 그래서 아빠 연기를 할 땐 경험적으로 확신이 있었어요. 그런데 아들 가진 아빠와 딸 가진 아빠는 자식을 대하는 태도가 확실히 다르더라고요. 저한테 육아는 육체적으로 힘이 많이 드는 일입니다. 근데 딸 가진 아빠들의 육아는 조곤조곤 이야기를 하는 느낌이랄까요. 그래서 딸을 둔 아빠들을 많이 관찰했어요. 그런 것들을 연기에 반영하려고 했고요.&quot;<br /><br />재혁이라는 인물의 또 한 가지 특징이라면 비행 공포증이 있다는 점이다. 과거에 겪은 어떤 일 때문에 일종의 공황장애가 생긴 것이다. 이병헌은 20대 중반에 공황장애를 실제로 겪었다고 했다. 이 부분 역시 경험한 것들이 있어서 표현하는 데 도움이 됐다고 했다. &quot;재혁이 겪는 것을 관객도 느끼게 해줘야 한다고 생각했습니다. 과호흡 증상, 그러다 보면 나오는 굳어진 표정과 눈빛, 굉장히 불안해 하는 모습들, 이런 걸 다 보여줘야 했죠. 그러면서 재혁의 감정을 대사로 전하는 게 관건이었습니다.&quot;<br /><br />&#039;비상선언&#039;은 비행기 내에서 벌어진 테러를 통해 인간 본질을 보여주는 시도를 한다. 어떤 사람은 이기적이지만 또 다른 누군가는 남을 위해 희생한다. 그리고 많은 이들이 함께 힘을 합쳐 난관을 이겨내려고 한다. 이병헌은 &quot;재난은 예측할 수도 없고 예고도 없이 찾아오잖아요. 그건 막을 수 없어요. 중요한 건 그 재난을 어떻게 헤쳐나가느냐일 겁니다. 이 영화는 우리에게 닥친 어려움을 어떻게 이겨낼 수 있는지에 관해 이야기한다고 생각해요.&quot;<br />\n◎공감언론 뉴시스 jb@newsis.com","date":"2022-07-31T05:48:00.000Z","url":"http://www.newsis.com/view?id=NISX20220729_0001961593"},{"spec":{"publisher":{"id":"newsis","name":"뉴시스","type":"통신사","url":"https://newsis.com"},"title":"연예","categories":["entertainment"],"url":"https://newsis.com/RSS/entertain.xml"},"title":"김호중 &quot;큰 사고&quot;…성대 이상에 옷까지 속 썪여…&#039;당나귀 귀&#039;","partialText":"<p><a href=\"http://image.newsis.com/2022/07/29/NISI20220729_0001053157_web.jpg?rnd=20220729172444\"><img border=\"0\" src=\"http://image.newsis.com/2022/07/29/NISI20220729_0001053157_web.jpg?rnd=20220729172444\" width=\"130\" /></a></p><br />[서울=뉴시스]황지향 인턴 기자 = 성악가로 돌아온 ‘트바로티’ 김호중의 무대가 공개된다.<br /><br />31일 오후 5시에 방송되는 KBS 2TV 예능 프로그램 &#039;사장님 귀는 당나귀 귀&#039;에서 김호중은 플라시도 도밍고와 함께 부르는 듀엣곡 외에 &#039;네순 도르마(Nesun Dorma) 공주는 잠 못 이루고&#039;와 지금껏 선보이지 않았던 &#039;람메르무어의 루치아(Lucia di Lammermoor)를 솔로곡으로 선보이며 성악의 세계로 초대할 예정이다.<br /><br />하지만 앞서 김호중은 도밍고와의 듀엣곡 연습에서는 악보가 준비되지 않는가 하면 목에 이상이 생기는 등 문제가 연달아 일어난데다 공연 당일 관객들의 입장 시간이 당겨지면서 리허설 마저 취소돼 무반주로 마이크 음량만 체크하고 연습을 전혀 하지 못해 걱정을 불러온 상황이 발생한다. <br /><br />게다가 김호중이 이날 공연을 위해 특별 제작한 셔츠에 문제가 발생하면서 절친의 옷을 빌려 입고 무대에 오를 수밖에 없어 당시 영상을 보며 &quot;지금은 웃을 수 있지만 정말 큰 사고였다&quot;고 회상한다.<br /><br />또 김호중은 제작진과의 인터뷰에서 &quot;그냥 성악 흉내만 내면 공연을 망치는 거잖아요&quot;라며 성악가로서 굳은 의지를 다져 기대를 더하고 있다.<br />\n◎공감언론 뉴시스 hjhj7289@newsis.com","date":"2022-07-31T03:20:00.000Z","url":"http://www.newsis.com/view?id=NISX20220729_0001961770"},{"spec":{"publisher":{"id":"newsis","name":"뉴시스","type":"통신사","url":"https://newsis.com"},"title":"연예","categories":["entertainment"],"url":"https://newsis.com/RSS/entertain.xml"},"title":"NCT 도영, 보이스피싱 상황극 중 겁에 질려…왜?","partialText":"<p><a href=\"http://image.newsis.com/2022/07/30/NISI20220730_0001053373_web.jpg?rnd=20220730154732\"><img border=\"0\" src=\"http://image.newsis.com/2022/07/30/NISI20220730_0001053373_web.jpg?rnd=20220730154732\" width=\"130\" /></a></p><br />[서울=뉴시스]송윤세 기자 = 그룹 &#039;NCT&#039; 멤버 도영이 상황극에 도전했다가 겁에 질렸다.<br /><br />31일 오후 6시30분 방송되는 SBS TV 예능물 &#039;집사부일체&#039;에는 생활 속 법률 지식을 알려줄 법 전문가 &#039;변호사 군단&#039;이 사부로 출연한다. 이승기, 양세형, 김동현, 은지원, 도영은 서울 가정행정법원을 찾아 법률에 대한 모든 것을 알려줄 초특급 변호사 군단 3인방을 사부로 마주했다. <br /><br />현재까지 약 1만여 건의 이혼 상담과 1000건의 이혼 소송을 진행한 이혼·가사법 전문 이인철 변호사, 형사 사건 담당 검사 출신으로 형사법 전문 윤정섭 변호사, 대한민국 최초의 재심 전문 변호사 박준영가 그들이다. 이인철 변호사는 &quot;오늘 방송만 보시면 모두가 준 변호사가 될 수 있을 것&quot;이라며 자신만만하게 포부를 밝혔다.<br /><br />&#039;법사부일체&#039; 특집으로 진행되는 이날 방송에서는 변호사 사부들을 통해 알아두면 유용한 법률 지식을 다룰 예정이다. 윤정섭 변호사는 나날이 발전하고 있는 사기 사건들의 수법과 그 예방법을 알려주기 위해 도영과 함께 상황극을 펼쳤다. 도영은 &quot;사기에 당하지 않을 자신이 있다&quot;며 자신만만하게 상황극을 시작했지만 끝내 겁에 질린 모습을 보여 사기 사건들의 위험성을 제대로 알려주었다는 후문이다.<br />\n◎공감언론 뉴시스 knaty@newsis.com","date":"2022-07-31T03:05:00.000Z","url":"http://www.newsis.com/view?id=NISX20220730_0001962117"},{"spec":{"publisher":{"id":"newsis","name":"뉴시스","type":"통신사","url":"https://newsis.com"},"title":"연예","categories":["entertainment"],"url":"https://newsis.com/RSS/entertain.xml"},"title":"&quot;오늘은 혼나는 날&quot; 충암고, 최강 몬스터즈에 설욕 다짐","partialText":"<p><a href=\"http://image.newsis.com/2022/07/29/NISI20220729_0001052949_web.jpg?rnd=20220729144818\"><img border=\"0\" src=\"http://image.newsis.com/2022/07/29/NISI20220729_0001052949_web.jpg?rnd=20220729144818\" width=\"130\" /></a></p>[서울=뉴시스]유다연 인턴 기자 = 충암고등학교가 최강 몬스터즈와의 재 맞대결을 앞두고 남다른 각오를 드러낸다. <br /><br />8월 1일 오후 10시30분에 방송되는 JTBC &#039;최강야구&#039;에서 최강몬스터즈와 충암고가 49일만에 맞대결을 펼친다. <br /><br />경기에 앞서 이영복 감독은 &quot;1차전에 져서 마음 아프게 지냈다&quot;며 &quot;오늘 비장한 각오로 나왔다&quot;고 밝혔다. 또한 &quot;우리 선수들은 감독보다도 더 준비를 잘 해왔다. 오늘 게임을 보면 아실 것&quot;이라며 &quot;오늘은 (최강 몬스터즈가) 혼나는 날이다&quot;라고 승리를 자신한다. <br /><br />이날 경기에서 이영복 감독은 입담으로 최강 몬스터즈를 견제하며 이승엽 감독과 신경전을 펼친다. <br /><br />특히 충암고 좌완 에이스 윤영철은 감독의 신뢰에 응답하며 과감한 몸쪽 승부는 물론, 허를 찌르는 체인지업까지 완벽한 제구와 속구를 앞세워 청소년 국가대표에 선발된 이유를 몸소 선보인다. <br /><br />윤영철의 공을 본 김선우 해설위원은 메이저리거 류현진을 언급하며 극찬한다. 최강 몬스터즈 선수들 역시 실력에 감탄하며 레전드의 위엄을 보여주기 위해 방망이를 쥔 손에 힘을 더한다. <br /><br />과연 청룡기 결승까지 올랐던 충암고등학교가 최강 몬스터즈에게 1차전 패배를 설욕할 수 있을지 호기심을 자아낸다.<br />\n◎공감언론 뉴시스 willow66@newsis.com","date":"2022-07-31T02:05:00.000Z","url":"http://www.newsis.com/view?id=NISX20220729_0001961459"},{"spec":{"publisher":{"id":"newsis","name":"뉴시스","type":"통신사","url":"https://newsis.com"},"title":"연예","categories":["entertainment"],"url":"https://newsis.com/RSS/entertain.xml"},"title":"&#039;데뷔 10주년&#039; 에일리, 윤상과 한솥밥","partialText":"<p><a href=\"http://image.newsis.com/2022/07/30/NISI20220730_0001053409_web.jpg?rnd=20220730224920\"><img border=\"0\" src=\"http://image.newsis.com/2022/07/30/NISI20220730_0001053409_web.jpg?rnd=20220730224920\" width=\"130\" /></a></p>[서울=뉴시스]이재훈 기자 = 래퍼 겸 가수 라비의 소속사 더라이브레이블과 최근 전속 계약이 만료된 가수 에일리(Ailee)가 프로듀서 겸 작곡가 윤상과 한솥밥을 먹는다. <br /><br />콘텐츠 기업 위지윅스튜디오 자회사이자 윤상 소속된 팝뮤직은 &quot;최근 에일리와 전속계약을 체결했다&quot;라고 30일 밝혔다.<br /><br />에일리도 이날 소셜 미디어에 &quot;더라이브레이블과의 전속계약 만료로 인해 소속사 이적을 하게 됐다. 새 소속사 팝뮤직에서 더 성숙하고 멋진 에일리가 되도록 노력하겠다. 우리 에일리언(공식 팬덤명) 언제나 기다려주고 믿어줘서 진심으로 감사하고 사랑한다&quot;고 적었다.<br /><br />에일리는 올해 데뷔 10주년을 맞았다. 지난 2012년 &#039;헤븐(Heaven)&#039;으로 데뷔해  &#039;보여줄게&#039;, &#039;U&I&#039;, &#039;노래가 늘었어&#039;, &#039;손대지 마&#039;, &#039;첫눈처럼 너에게 가겠다&#039; 등의 히트곡을 냈다. JTBC &#039;유명가수전-배틀어게인&#039;, KBS 2TV &#039;불후의 명곡&#039;, &#039;리슨 업(Listen-Up)&#039; 등 음악 프로그램에 꾸준히 나왔다. <br /><br />현재 팝뮤직엔 윤상을 비롯해 일렉 팝 그룹 &#039;클래지콰이 프로젝트&#039;, 3인조 혼성 보컬 그룹 &#039;스웨이(SWAY)&#039;, 배우 허규와 송주희(Alice), 신인 걸그룹 첫사랑(CSR), 인플루언서 유리사(YURISA) 등이 소속됐다. 오는 9월16일 개막하는 뮤지컬 &#039;사랑의 불시착&#039;도 제작 중이다.<br />\n◎공감언론 뉴시스 realpaper7@newsis.com","date":"2022-07-31T01:58:00.000Z","url":"http://www.newsis.com/view?id=NISX20220730_0001962240"},{"spec":{"publisher":{"id":"newsis","name":"뉴시스","type":"통신사","url":"https://newsis.com"},"title":"연예","categories":["entertainment"],"url":"https://newsis.com/RSS/entertain.xml"},"title":"이천수, 부모 냉전에 충격…母 &quot;졸혼까지 생각&quot;(종합)","partialText":"<p><a href=\"http://image.newsis.com/2022/07/30/NISI20220730_0001053350_web.jpg?rnd=20220730134850\"><img border=\"0\" src=\"http://image.newsis.com/2022/07/30/NISI20220730_0001053350_web.jpg?rnd=20220730134850\" width=\"130\" /></a></p>[서울=뉴시스]송윤세 기자 = 전 축구선수 이천수가 자신의 부모 관계를 회북시키기 위해 고군분투했다. <br /><br />30일 오후 9시20분 방송한 KBS 2TV &#039;살림하는 남자들&#039; 시즌2에서 이천수는 본가에 들렀다가 혼자 있는 아버지로부터 어머니와 한 달 가까이 냉전이 이어지고 있다는 이야기를 듣고 근심에 빠진다. <br /><br />더군다나 자신의 연락을 받고 집에 돌아온 어머니가 &#039;졸혼까지 생각하고 있다&#039;는 속마음을 털어놔 충격까지 받는다. 이를 듣던 아버지는 &quot;말 같지도 않은 소리&quot;라며 자리를 박차고 일어났다. <br /><br />생각보다 심각한 부모님의 상황에 고민하던 이천수는 두 분의 연애 시절 추억의 장소로 모셔가 좋았던 기억을 떠올리게 하는 작전을 계획했다. <br /><br />이후 부모님과 함께 길을 나선 이천수는 한 장소에서 어린 시절을 떠올리며 즐거워했다. 부모는 예전에 사진을 찍었전 포즈와 같은 동작으로 사진을 찍기도 했다. <br /><br />그런데 이천수는 갑자기 &quot;모두 내 책임인 것 같다&quot;며 표정이 어두워졌다.  이천수가 꼽은 추억의 장소 중 한 곳에 도착한 어머니는 &quot;천수가 너무 어린 나이에 고생한 곳&quot;이라며 가슴 아파하기도 했다. <br /><br />&#039;살림남&#039;은 신세대 남편부터 중년 그리고 노년의 남편들의 리얼 살림기를 담은 프로그램이다.<br />\n◎공감언론 뉴시스 knaty@newsis.com","date":"2022-07-31T00:00:00.000Z","url":"http://www.newsis.com/view?id=NISX20220730_0001962242"},{"spec":{"publisher":{"id":"newsis","name":"뉴시스","type":"통신사","url":"https://newsis.com"},"title":"연예","categories":["entertainment"],"url":"https://newsis.com/RSS/entertain.xml"},"title":"채리나, 코로나 확진에 씁쓸…&quot;임테기면 얼마나 좋겠니&quot;","partialText":"<p><a href=\"http://image.newsis.com/2022/03/03/NISI20220303_0000944504_web.jpg?rnd=20220303164737\"><img border=\"0\" src=\"http://image.newsis.com/2022/03/03/NISI20220303_0000944504_web.jpg?rnd=20220303164737\" width=\"130\" /></a></p>[서울=뉴시스]전재경 기자 = 그룹 &#039;룰라&#039; 출신 가수 채리나가 코로나19에 확진됐다. <br /><br />채리나는 30일 자신의 인스타그램 스토리에 &quot;임테기(임신테스트기)면 얼마나 좋겠니, 지금 무척 아야 중&quot;이라는 글이 적힌 한 장의 사진을 게재했다.<br /><br />사진엔 두 줄이 선명하게 새겨진 코로나19 자가진단키트 결과가 포착됐다. 채리나는 지난 2016년 6세 연하인 야구선수 출신 박용근과 결혼했다. 그녀는 난임을 겪고 있다며 임신을 위해 노력 중이라고 했다. <br /><br />채리나는 최근 종영한 SBS TV &#039;골 때리는 외박&#039;에 출연하는 등 다수 예능에서 활약 중이다. <br /><br />한편 최근 코로나19가 다시 확산하면서 연예계에도 확진자가 늘고 있다.<br />\n◎공감언론 뉴시스 for3647@newsis.com","date":"2022-07-30T23:10:02.000Z","url":"http://www.newsis.com/view?id=NISX20220730_0001962248"},{"spec":{"publisher":{"id":"newsis","name":"뉴시스","type":"통신사","url":"https://newsis.com"},"title":"연예","categories":["entertainment"],"url":"https://newsis.com/RSS/entertain.xml"},"title":"&#039;썸바디2&#039; 이예나, 10월 결혼 앞두고 혼전임신","partialText":"<p><a href=\"http://image.newsis.com/2022/07/30/NISI20220730_0001053408_web.jpg?rnd=20220730222605\"><img border=\"0\" src=\"http://image.newsis.com/2022/07/30/NISI20220730_0001053408_web.jpg?rnd=20220730222605\" width=\"130\" /></a></p>[서울=뉴시스]김현숙 인턴 기자 = 배우 이예나(30)가 결혼을 앞두고 임신 소식을 전했다.<br /><br />이예나는 30일 자신의 소셜 미디어에 &quot;저희에게 소중한 생명이 먼저 찾아왔다. 알콩이. 아빠가 된 거 축하한다&quot;고 적었다. <br /><br />자신의 뱃속에 있는 아기의 초음파 사진을 함께 올렸다. 이예나는 오는 10월29일 결혼한다고 지난달 밝혔다. 예비 신랑은 8세 연상 프로볼링 선수로 알려졌다. <br /><br />이예나는 지난 2004년 아역 배우로 데뷔했다. 드라마 &#039;단 하나의 사랑&#039;, &#039;부잣집 아들&#039; 등에 출연했다. 무용을 전공했다. 춤과 연애 예능을 결합한 엠넷 &#039;썸바디2&#039;를 통해 주목 받았다.<br />\n◎공감언론 뉴시스 esther@newsis.com","date":"2022-07-30T22:33:08.000Z","url":"http://www.newsis.com/view?id=NISX20220730_0001962076"},{"spec":{"publisher":{"id":"newsis","name":"뉴시스","type":"통신사","url":"https://newsis.com"},"title":"연예","categories":["entertainment"],"url":"https://newsis.com/RSS/entertain.xml"},"title":"쌈디, 55.3㎏ 몸무게 인증…이러다 뼈만 남겠네","partialText":"<p><a href=\"http://image.newsis.com/2022/07/30/NISI20220730_0001053395_web.jpg?rnd=20220730182905\"><img border=\"0\" src=\"http://image.newsis.com/2022/07/30/NISI20220730_0001053395_web.jpg?rnd=20220730182905\" width=\"130\" /></a></p><br />[서울=뉴시스]송윤세 기자 = 가수 사이먼 도미닉(쌈디, 본명 정기석)가 50㎏대의 몸무게를 공개했다. <br /><br />쌈디는 29일 인스타그램에 &quot;말라깽이&quot;라는 문구와 함께 자신의 모습을 담은 여러 장의 사진을 올렸다. 갸름한 턱선과 군살 없이 마른 몸매가 눈길을 모았다. 특히 그는 55.3㎏이라는 수치기 찍힌 저울 사진도 함께 게재했다. <br /><br />해당게시물에 누리꾼들은 &quot;너무 마른 거 아니에요?&quot; &quot;오빠 팍팍 좀 먹어요.. 하&quot; &quot;55.3㎏ 실화냐?&quot;라며 걱정하는 댓글을 달았다. <br /><br />한편 쌈디는 티빙 웹예능 &#039;환승연애2&#039;에 MC로 출연하고 있다.<br />\n◎공감언론 뉴시스 knaty@newsis.com","date":"2022-07-30T22:20:25.000Z","url":"http://www.newsis.com/view?id=NISX20220730_0001962210"},{"spec":{"publisher":{"id":"newsis","name":"뉴시스","type":"통신사","url":"https://newsis.com"},"title":"연예","categories":["entertainment"],"url":"https://newsis.com/RSS/entertain.xml"},"title":"이준호, 생애 첫 낚시 도전…조혜련·박미선도 출격","partialText":"<p><a href=\"http://image.newsis.com/2022/07/30/NISI20220730_0001053383_web.jpg?rnd=20220730170823\"><img border=\"0\" src=\"http://image.newsis.com/2022/07/30/NISI20220730_0001053383_web.jpg?rnd=20220730170823\" width=\"130\" /></a></p><br />[서울=뉴시스]송윤세 기자 = &#039;도시어부&#039;의 절친이 대거 출연해 낚시에 도전한다.  <br /><br />30일 오후 10시20분에 방송하는 채널A 예능 &#039;나만 믿고 따라와, 도시어부 시즌4&#039; 4회에서는 절친 특집으로 개그우먼 박미선, 조혜련, 가수 겸 배우 이준호와 함께 민물낚시 대결을 벌이는 모습이 그려진다.<br /><br />드라마 &#039;옷소매 붉은 끝동&#039;에서 여심 저격에 성공한 이준호는 극 중 할아버지와 손자로 호흡을 맞춘 이덕화와 짝꿍이 돼 낚시 대결을 펼쳤다. 이준호는 젊은 패기로 호기롭게 생애 첫 낚시에 도전했지만 계속되는 노피쉬 사태로 &#039;꽝준호&#039;라는 별명까지 얻게 됐다. 심지어 계속된 챔질 실패에 결국 울분을 삼키지 못하고 포효까지 해 보는 이들의 웃음을 자아냈다는 후문이다. <br /><br />아울러 의리로 뭉쳐 모두가 기대했던 이덕화와 이준호의 브로 케미에 금이 갈 뻔한 위기도 있었다. 낚시에 진심인 이덕화가 계속해서 실수로 물고기를 놓치는 이준호를 향해 처음으로 욱 버럭하며 화를 냈던 것. 과연 이준호는 &#039;버럭 덕화&#039;와 함께 무사히 낚시를 마무리 할 수 있을지 결과가 주목된다.<br /><br />이어 이경규와 조혜련 팀인 일명 &#039;경련 커플&#039;도 눈길을 끌었다. 이경규는 조혜련이 처음 등장 하자마자 &quot;내 지인 아니야!&quot;라고 부정하며 사상 초유의 팀 거부 사태까지 일으켜 모두를 폭소케 했다. 끊임없이 밀어내는 이경규의 옆에서 조혜련은 그에 굴하지 않고 끈질기게 이경규에게 애정공세를 하며 마음을 얻으려 노력해 짠내를 유발했다. <br /><br />한편, 이태곤의 의외의 절친으로 박미선이 낚시터를 찾았다. 타 방송에서 함께 MC로 호흡을 맞춘 두 사람은 한 팀이 되어 낚시대결을 진행했다. 박미선이 &quot;제 별명이 어복녀예요&quot;라고 밝히자, 이태곤은 다른 팀으로부터 부러움을 한 몸에 샀다.<br />\n◎공감언론 뉴시스 knaty@newsis.com","date":"2022-07-30T21:30:00.000Z","url":"http://www.newsis.com/view?id=NISX20220730_0001962179"},{"spec":{"publisher":{"id":"newsis","name":"뉴시스","type":"통신사","url":"https://newsis.com"},"title":"연예","categories":["entertainment"],"url":"https://newsis.com/RSS/entertain.xml"},"title":"웹툰 작가 박태준·야옹이, 연기가 부업?…&#039;오늘의 웹툰&#039;","partialText":"<p><a href=\"http://image.newsis.com/2022/07/30/NISI20220730_0001053382_web.jpg?rnd=20220730170445\"><img border=\"0\" src=\"http://image.newsis.com/2022/07/30/NISI20220730_0001053382_web.jpg?rnd=20220730170445\" width=\"130\" /></a></p>[서울=뉴시스]김현숙 인턴 기자 = 스타 웹툰 작가 박태준과 야옹이가 웹툰 주제 드라마에 출연한다. <br /><br />30일 SBS에 따르면, 박태준·야옹이 작가는 이날 오후 10시에 방송되는 SBS TV 금토 드라마 &#039;오늘의 웹툰&#039;(극본 조예랑·이재은, 연출 조수원·김영환, 기획 스튜디오S, 제작 빈지웍스, 스튜디오N) 2회에 출연한다. <br /><br />&#039;오늘의 웹툰&#039;은 오늘의 웹툰을 업로드하기 위한 웹툰 업계의 역동적인 오피스 라이프를 그린다. 그 세계에 발을 들인 유도 선수 출신 새내기 웹툰 편집자 &#039;온마음&#039;(김세정)의 레벨업 성장기가 주축이다. <br /><br />전날 첫 방송에서는 온마음이 일하는 백어진(김갑수), 나강남(임철수), 뽐므(하율리) 등 네온 웹툰 편집부 내 다양한 작가의 캐릭터가 그려졌다. <br /><br />이날 2회에서는 박태준·야옹이 작가가 사실적인 웹툰 작가의 세계를 연기한다. 새내기 편집자 &#039;구준영&#039;(남윤수)의 에피소드가 전개된다. <br /><br />제작진은 &quot;만화가의 상징 &#039;빵모자&#039;로 멋을 살린 박태준 작가와 실제로 작업할 때처럼 편안한 의상을 입은 야옹이 작가가 뛰어난 비주얼만큼 훌륭한 연기를 선보였다&quot;면서 &quot;특히 실제 웹툰 작가의 작업실에서 촬영이 진행되면서, 극의 리얼리티가 한층 더 높아졌다&quot;고 귀띔했다. <br /><br />박태준 작가는 &#039;얼짱&#039; 모델 출신으로 네이버웹툰 &#039;외모지상주의&#039; 등 화제작을 연재했다. 야옹이 작가는 네이버웹툰 &#039;여신강림&#039;으로 이름을 알렸다. 작품 속 캐릭터보다 더 여신 같은 미모로, 인플루언서로도 활약 중이다. <br /><br />제작진은 &quot;2회에선 웹툰 작가와 편집자의 관계성이 부각되면서, 실제 작가를 섭외해 리얼리티를 높이고자 특별 출연을 기획했다&quot;면서 &quot;두 분의 작가가 드라마의 내용을 듣고 흔쾌히 섭외에 응했다&quot;고 전했다.<br />\n◎공감언론 뉴시스 esther@newsis.com","date":"2022-07-30T21:00:00.000Z","url":"http://www.newsis.com/view?id=NISX20220730_0001962169"},{"spec":{"publisher":{"id":"newsis","name":"뉴시스","type":"통신사","url":"https://newsis.com"},"title":"연예","categories":["entertainment"],"url":"https://newsis.com/RSS/entertain.xml"},"title":"&#039;댄스폭주 기관차&#039; 이은지·&#039;반전가득 농염몸짓&#039; 비비…&#039;놀토&#039;","partialText":"<p><a href=\"http://image.newsis.com/2022/07/30/NISI20220730_0001053358_web.jpg?rnd=20220730145756\"><img border=\"0\" src=\"http://image.newsis.com/2022/07/30/NISI20220730_0001053358_web.jpg?rnd=20220730145756\" width=\"130\" /></a></p><br />[서울=뉴시스]송윤세 기자 = 개그우먼 이은지, 가수 지코, 비비, 안유진이 화려한 퍼포먼스를 펼친다. <br /><br />30일 오후 7시30분 방송하는 tvN &#039;놀라운 토요일&#039;에 이은지, 지코, 비비, 안유진이 출격한다. 여름 특집을 위해 새롭게 단장한 스튜디오에서 전에는 없었던 다양한 이벤트들이 예고되며 도레미들이 회식 같은 분위기에서 야유회를 즐기는 모습도 공개됐다.<br /><br />본격적인 받아쓰기에 앞서 게스트들은 도레미들과 인연을 소개했다. 이은지는 &quot;존경하는 도레미가 있다&quot;며 문세윤을 꼽았다. 지코와 키는 같은 성향의 MBTI답게 서로의 마음을 읽으며 공감해 눈길을 끌었다. 안유진은 김동현과 군대 서바이벌 프로그램에서 함께 MC를 맡았던 경험담을 공유했다. &quot;미필인 제가 김동현으로부터 군대 관련 설명을 듣고 싶었는데, 오히려 저에게 계속 질문했다&quot;며 &quot;오늘도 많이 도와드리겠다&quot;고 덧붙여 웃음을 안겼다.<br /><br />화기애애한 분위기 속 이날 받쓰에는 안유진이 &quot;여름마다 듣는다&quot;는 노래가 출제됐다. 안유진의 폭풍 받쓰로 기대감이 고조된 상황에 김동현은 &quot;저도 작년에 열심히 예습했던 노래&quot;라며 경쟁 구도를 형성했다. 완벽한 엔딩 요정의 면모마저 보여준 안유진, &#039;놀토&#039; 특집마다 활약상을 보여준 김동현과 더불어 &#039;문맥의 신&#039; 신동엽, &#039;키어로&#039; 키의 존재감도 흥미를 돋웠다. 이 밖에 애드리브 랩으로 탄성을 자아낸 지코, &quot;제 혈관에 국밥 국물이 흐른다&quot;며 시장 음식을 향한 열정으로 받쓰에 몰입한 비비, 흥 넘치는 리액션과 참신한 개인기 퍼레이드를 방출한 이은지가 이목을 사로잡았다.<br /><br />이어 무더위를 날려줄 시원한 계곡에서 제1회 &#039;놀토&#039; 하계 야유회가 열렸다. 침샘 폭발 안주 3종과 역대급 경품이 걸린 야유회에는 &#039;회식 게임 - 부장님 퀴즈&#039;가 등장했다. tvN 예능국 부장이 2년 반 동안 꾸준히 제안했다는 기상천외한 아재 감성의 문제들이 반복되자 도레미들이 원성을 터뜨려 폭소를 선사했다.<br /><br />이후 &#039;노래방 반주 퀴즈&#039;도 나왔다. 지코는 계곡에서 맨발 퍼포먼스를 선보였고, 이은지는 댄스 폭주 기관차의 모습을 뽐냈다. 비비의 반전미 가득한 농염한 몸짓에는 &quot;화끈하다&quot;는 탄성이 터져 나왔다. 안유진 역시 박나래, 이은지와 현란한 댄스 배틀을 벌이자, 도레미들이 이구동성으로 &quot;진짜 회식 같다&quot;고 외쳤다.<br />\n◎공감언론 뉴시스 knaty@newsis.com","date":"2022-07-30T19:00:00.000Z","url":"http://www.newsis.com/view?id=NISX20220730_0001962114"},{"spec":{"publisher":{"id":"newsis","name":"뉴시스","type":"통신사","url":"https://newsis.com"},"title":"연예","categories":["entertainment"],"url":"https://newsis.com/RSS/entertain.xml"},"title":"&quot;깜짝 놀라&quot;…정태우, ♥장인희 유방암 조직 검사에 &#039;심란&#039;","partialText":"<p><a href=\"http://image.newsis.com/2022/07/30/NISI20220730_0001053392_web.jpg?rnd=20220730175922\"><img border=\"0\" src=\"http://image.newsis.com/2022/07/30/NISI20220730_0001053392_web.jpg?rnd=20220730175922\" width=\"130\" /></a></p>[서울=뉴시스]김현숙 인턴 기자 = 배우 정태우가 아픈 아내를 위해 일일 요리사로 변신한다. <br /><br />30일 오후 9시20분 방송하는 KBS 2TV 예능 &#039;살림하는 남자들&#039; 시즌2(살림남2)에서 정태우는 지난해 유방암 검사를 받았던 장인희로부터 자가 촉진 중 이상을 발견했다는 말을 듣고 걱정스러운 마음에 곧바로 함께 병원을 찾았다.<br /><br />두 사람은 검사 결과 촉진했던 부위보다 다른 곳이 더 우려된다는 얘기를 듣고 깜짝 놀란다. 예상치 못한 조직 검사까지 받게 되면서 심란해했다고.<br /><br />이후 집으로 돌아온 정태우는 아내가 푹 쉴 수 있게 설거지부터 식사까지 자신이 집안일을 맡겠다고 큰소리 친다. 하지만 장인희는 평소 살림만 했다 하면 일을 크게 벌이는 정태우를 못 미더워했다는데.<br /><br />두 아들에게도 도움을 요청한 정태우는 휴대 전화 검색을 통해 벼락치기로 레시피를 익혀 생애 첫 전복죽 만들기에 도전했다.<br /><br />제작진은 &quot;그런 가운데 옆에서 요리를 도와주던 첫째 하준이는 &#039;조심 좀 하지&#039;라 잔소리를 하고, 둘째 하린이는 지쳐 의자에 누워 버렸다&quot;면서 &quot;이날 저녁 주방에서는 무슨 일이 있었던 것인지 방송에서 확인해달라&quot;고 청했다.<br />\n◎공감언론 뉴시스 esther@newsis.com","date":"2022-07-30T18:04:01.000Z","url":"http://www.newsis.com/view?id=NISX20220730_0001962207"},{"spec":{"publisher":{"id":"newsis","name":"뉴시스","type":"통신사","url":"https://newsis.com"},"title":"연예","categories":["entertainment"],"url":"https://newsis.com/RSS/entertain.xml"},"title":"김호중, 도밍고 대화 중 울컥…뭐라고 했길래","partialText":"<p><a href=\"http://image.newsis.com/2022/07/30/NISI20220730_0001053386_web.jpg?rnd=20220730172707\"><img border=\"0\" src=\"http://image.newsis.com/2022/07/30/NISI20220730_0001053386_web.jpg?rnd=20220730172707\" width=\"130\" /></a></p><br />[서울=뉴시스]송윤세 기자 = 세계적인 성악가 플라시도 도밍고가 김호중을 울컥하게 만들었다. <br /><br />31일 오후 5시 방송하는 KBS 2TV 예능 &#039;사장님 귀는 당나귀 귀&#039;에서는 &#039;한국의 파바로티&#039; 김호중과 도밍고가 함께 하는 공연 현장이 공개된다. 이날 6200석을 가득 채운 관객들의 환호성이 쏟아진 가운데 도밍고가 먼저 대가다운 기품이 묻어나는 솔로곡 무대로 막을 열었다. <br /><br />자신의 우상이었던 도밍고의 무대를 누구보다 가까이에서 지켜본 김호중은 &quot;청년의 목소리라고 해도 믿어질 정도&quot;라며 감탄했다. 다음 차례를 기다리며 긴장한 김호중에게 주먹을 불끈 쥐며 격려와 조언을 아끼지 않는 도밍고와 무대 안팎에서 도밍고를 살뜰히 챙기는 김호중의 모습을 본 출연진들은 &quot;할아버지와 손자 같다&quot;며 흐뭇한 미소를 지었다.<br /><br />김호중은 &quot;&#039;걱정하지마라. 이미 쇼는 시작됐다&#039;는 도밍고의 말이 용기를 북돋아주었다&quot;며 감사 인사를 전했다. 듀엣 공연의 마지막 곡인 &#039;마이 웨이&#039;를 부르던 중 김호중이 갑자기 도밍고에게 다가서는 돌발 상황도 생겨 이에 대한 뒷이야기도 밝혀질 예정이다.<br /><br />한편, 공연이 끝난 뒤 자신의 대기실을 찾아온 도밍고와 대화를 나누던 김호중이 울컥하는 모습을 보고 의아해하던 출연진들은 번역된 영상 속 자막을 보고 깜짝 놀랐다는 후문이다.<br />\n◎공감언론 뉴시스 knaty@newsis.com","date":"2022-07-30T17:55:18.000Z","url":"http://www.newsis.com/view?id=NISX20220730_0001962192"},{"spec":{"publisher":{"id":"newsis","name":"뉴시스","type":"통신사","url":"https://newsis.com"},"title":"연예","categories":["entertainment"],"url":"https://newsis.com/RSS/entertain.xml"},"title":"WSG워너비 박진주, 붕어빵 부모 등장…&quot;집에서도 아이돌 빙의&quot;","partialText":"<p><a href=\"http://image.newsis.com/2022/07/30/NISI20220730_0001053381_web.jpg?rnd=20220730170423\"><img border=\"0\" src=\"http://image.newsis.com/2022/07/30/NISI20220730_0001053381_web.jpg?rnd=20220730170423\" width=\"130\" /></a></p><br />[서울=뉴시스]송윤세 기자 = 배우 박진주의 아버지가 딸이 집에서도 아이돌에 빙의돼 있다고 폭로했다. <br /><br />30일 오후 6시25분 방송하는 MBC TV 예능물 &#039;놀면 뭐하니?&#039;에서는 WSG워너비가 땀 흘리며 준비한 대망의 콘서트 무대가 베일을 벗는다. 공개된 사진에 관객석에 앉은 WSG워너비 가족, 친구, 지인들이 인터뷰하는 모습이 담겼다. <br /><br />&#039;숏박스&#039; 멤버 김원훈, 조진세는 &quot;(엄지윤이 아닌) 다른 멤버들을 보러 왔다&quot;며 티격태격 케미로 현장을 폭소하게 했다. 여기에 라붐, 써니힐 멤버들은 각각 소연, 코타가 그룹을 벗어나 WSG워너비 멤버로 활동하는 모습을 본 소감을 말해 눈길을 끌었다. 어반자카파 멤버 권순일, 박용인의 응원에 조현아는 &quot;창피하다&quot;고 솔직하게 말해 웃음을 안겼다. <br /><br />특히 박진주와 똑닮은 외모의 &#039;붕어빵&#039; 부모님 등장에 모두의 관심을 집중됐다. 유재석은 &quot;누가 봐도 진주 아버님, 어머님이시다&quot;며 놀라워했다. 박진주의 아버지는 &quot;(진주가) 집에서도 완전 아이돌에 빙의돼 있다&quot;며 마이크를 놓지 않는 토크 본능을 뽐내 현장을 들썩이게 했다.<br /><br />여기에 4FIRE의 열성팬으로 등장한 나비 남편도 웃음을 보탰다. 훈훈한 외모와 반전되는 나비 남편의 주접 응원에 신미나(신봉선)는 &quot;이래서 부부인가보다&quot;며 절로 고개를 끄덕였다. 또 엘레나 킴(김숙)은 쏠(SOLE)의 아버지에게 &quot;쏠이 오리지널 부산 출신이 맞냐&quot;고 물으며 확인 작업에 들어갔다.<br />\n◎공감언론 뉴시스 knaty@newsis.com","date":"2022-07-30T17:15:42.000Z","url":"http://www.newsis.com/view?id=NISX20220730_0001962167"},{"spec":{"publisher":{"id":"newsis","name":"뉴시스","type":"통신사","url":"https://newsis.com"},"title":"연예","categories":["entertainment"],"url":"https://newsis.com/RSS/entertain.xml"},"title":"전현무 &#039;주3회 먹은&#039; 메뉴·김숙 &#039;싸가는&#039; 떡볶이…방송국 맛집 어디?","partialText":"<p><a href=\"http://image.newsis.com/2022/07/30/NISI20220730_0001053377_web.jpg?rnd=20220730163731\"><img border=\"0\" src=\"http://image.newsis.com/2022/07/30/NISI20220730_0001053377_web.jpg?rnd=20220730163731\" width=\"130\" /></a></p><br />[서울=뉴시스]송윤세 기자 = 방송인 전현무와 개그우먼 김숙이 극찬하는 방송국 맛집을 공개한다. <br /><br />31일 오후 5시 방송하는 KBS 2TV 예능 &#039;사장님 귀는 당나귀 귀&#039;에서 정호영 셰프가 직장인들의 건강을 책임지는 회사 구내식당 메뉴에 도전했다. 정호영은 전국 650개 구내식당을 운영 중인 대기업으로부터 최근 입점 제안을 받아 기회를 잡기 위해 직원들과 신메뉴 개발에 돌입했다. 이후 정호영은 점심 시간에 간편하고 맛있게 먹을 수 있는 &#039;마제덮밥&#039;으로 메뉴를 결정하고 500명을 상대로 한 시범 판매를 위해 구내식당을 찾았다.<br /><br />하지만 구내식당 초보자인 정호영과 일식 셰프 군단은 시작부터 네 명이서 고기 50㎏, 달걀 750개 등 엄청난 양의 재료를 손질해야하는 난관에 부딪혔다. 요리를 하던 중에는 가스 불을 꺼뜨리는 등 실수를 연발해 이들이 점심 시간까지 남은 2시간 동안 음식을 완성해낼 수 있을지 결과에 이목이 집중된다.  <br /><br />한편 이날 녹화 현장에서는 아이돌의 최애 간식이라는 OO샌드위치부터 전현무가 &#039;전국에서 가장 맛있는 라면&#039;으로 꼽은 &#039;점저 라면’ 등 각 방송사별 최고의 한 끼에 대해 MC들이 이야기하며 열을 올렸다. <br /><br />김숙은 &#039;개그콘서트 할 때 무조건 싸갔다는 떡볶이&#039;를, 전현무는 KBS 아나운서 근무 당시 일주일에 세 번이나 먹었을 정도로 푹 빠졌던 이색 메뉴인 &#039;짜빠삼겹&#039;을 소개해 출연진들의 침샘을 폭발시켰다.<br />\n◎공감언론 뉴시스 knaty@newsis.com","date":"2022-07-30T17:02:40.000Z","url":"http://www.newsis.com/view?id=NISX20220730_0001962115"}]